{
  "applications": "*",
  "changelogDate": "20230321181111",
  "dto": "no",
  "embedded": false,
  "entityTableName": "schedule_event",
  "fields": [
    {
      "fieldName": "startTime",
      "fieldType": "Instant"
    },
    {
      "fieldName": "endTime",
      "fieldType": "Instant"
    },
    {
      "fieldName": "heading",
      "fieldType": "String"
    },
    {
      "fieldName": "date",
      "fieldType": "ZonedDateTime"
    },
    {
      "fieldName": "details",
      "fieldType": "String"
    }
  ],
  "fluentMethods": true,
  "jpaMetamodelFiltering": false,
  "name": "ScheduleEvent",
  "pagination": "no",
  "readOnly": false,
  "relationships": [
    {
      "otherEntityField": "login",
      "otherEntityName": "user",
      "relationshipName": "user",
      "relationshipType": "many-to-one"
    }
  ],
  "service": "no"
}
